LICENSE
MANIFEST.in
README
setup.py
src/django_vcstorage.egg-info/PKG-INFO
src/django_vcstorage.egg-info/SOURCES.txt
src/django_vcstorage.egg-info/dependency_links.txt
src/django_vcstorage.egg-info/top_level.txt
src/vcstorage/__init__.py
src/vcstorage/fields.py
src/vcstorage/storage.py