Metadata-Version: 1.0
Name: django-vcstorage
Version: 0.1.1
Summary: A Django app that provides file storage backends for Mercurial, Git and Bazaar by using anyvc.
Home-page: http://bitbucket.org/jezdez/django-vcstorage/
Author: Jannis Leidel
Author-email: jannis@leidel.info
License: BSD
Platform: UNKNOWN
Classifier: Development Status :: 4 - Beta
Classifier: Framework :: Django
Classifier: Intended Audience :: Developers
Classifier: License :: OSI Approved :: BSD License
Classifier: Operating System :: OS Independent
Classifier: Programming Language :: Python
Classifier: Topic :: Internet :: WWW/HTTP
